[{"category":"Fantasy"},
    {"category":"Adventure"},
    {"category":"Contemporary"},
    {"category":"Dystopian"},
    {"category":"Horror"},
    {"category":"Thriller"},
    {"category":"Paranormal"},
    {"category":"Historical fiction"},
    {"category":"Science Fiction"},
    {"category":"Memoir"},
    {"category":"Cooking"},
    {"category":"Art"},
    {"category":"Self-help / Personal"},
    {"category":"Development"},
    {"category":"Motivational"},
    {"category":"Health"},
    {"category":"History"},
    {"category":"Travel"},
    {"category":"Guide / How-to"},
    {"category":"Families & Relationships"},
    {"category":"Humor"},
    {"category":"Children’s"}

]